<?xml version="1.0" encoding="utf-8"?>
<TextureAtlas imagePath="gui.png">
	<!-- Created with Adobe Flash Professional version 14.1.0.96 -->
	<!-- http://www.adobe.com/products/flash.html -->
	<SubTexture name="battle_background" x="2071" y="1010" width="1000" height="720" pivotX="0" pivotY="0"/>
	<SubTexture name="battle_background_field" x="3072" y="1010" width="1000" height="720" pivotX="0" pivotY="0"/>
	<SubTexture name="battle_current_player" x="123" y="1830" width="28" height="24" pivotX="0" pivotY="0"/>
	<SubTexture name="battle_hit" x="1054" y="1479" width="232" height="259" pivotX="0" pivotY="0"/>
	<SubTexture name="battle_monster_button" x="791" y="1821" width="95" height="66" pivotX="0" pivotY="0"/>
	<SubTexture name="battle_progress_back" x="1287" y="1719" width="152" height="16" pivotX="0" pivotY="0"/>
	<SubTexture name="battle_progress_line" x="3447" y="1862" width="120" height="16" pivotX="0" pivotY="0"/>
	<SubTexture name="battle_stats" x="1" y="1792" width="121" height="48" pivotX="0" pivotY="0"/>
	<SubTexture name="battle_stats_icons" x="4075" y="707" width="20" height="36" pivotX="0" pivotY="0"/>
	<SubTexture name="boss" x="205" y="1857" width="80" height="75" pivotX="0" pivotY="0"/>
	<SubTexture name="camp" x="3983" y="1731" width="105" height="65" pivotX="0" pivotY="0"/>
	<SubTexture name="camp_background" x="2071" y="1" width="1650" height="1008" pivotX="0" pivotY="0"/>
	<SubTexture name="card_a1" x="384" y="1632" width="200" height="74" pivotX="0" pivotY="0"/>
	<SubTexture name="card_a2" x="585" y="1632" width="200" height="74" pivotX="0" pivotY="0"/>
	<SubTexture name="card_a3" x="1457" y="1688" width="200" height="74" pivotX="0" pivotY="0"/>
	<SubTexture name="card_a4" x="384" y="1707" width="200" height="74" pivotX="0" pivotY="0"/>
	<SubTexture name="card_am1" x="585" y="1707" width="200" height="74" pivotX="0" pivotY="0"/>
	<SubTexture name="card_m1" x="2978" y="1731" width="200" height="74" pivotX="0" pivotY="0"/>
	<SubTexture name="card_m10" x="3179" y="1731" width="200" height="74" pivotX="0" pivotY="0"/>
	<SubTexture name="card_m2" x="3380" y="1731" width="200" height="74" pivotX="0" pivotY="0"/>
	<SubTexture name="card_m3" x="3581" y="1731" width="200" height="74" pivotX="0" pivotY="0"/>
	<SubTexture name="card_m4" x="3782" y="1731" width="200" height="74" pivotX="0" pivotY="0"/>
	<SubTexture name="card_m5" x="1018" y="1739" width="200" height="74" pivotX="0" pivotY="0"/>
	<SubTexture name="card_m6" x="1219" y="1739" width="200" height="74" pivotX="0" pivotY="0"/>
	<SubTexture name="card_m7" x="1420" y="1763" width="200" height="74" pivotX="0" pivotY="0"/>
	<SubTexture name="card_m8" x="1977" y="1772" width="200" height="74" pivotX="0" pivotY="0"/>
	<SubTexture name="card_m9" x="2178" y="1772" width="200" height="74" pivotX="0" pivotY="0"/>
	<SubTexture name="card_s1" x="2379" y="1772" width="200" height="74" pivotX="0" pivotY="0"/>
	<SubTexture name="card_s2" x="2580" y="1772" width="200" height="74" pivotX="0" pivotY="0"/>
	<SubTexture name="card_s3" x="188" y="1782" width="200" height="74" pivotX="0" pivotY="0"/>
	<SubTexture name="card_s4" x="389" y="1782" width="200" height="74" pivotX="0" pivotY="0"/>
	<SubTexture name="card_s5" x="590" y="1782" width="200" height="74" pivotX="0" pivotY="0"/>
	<SubTexture name="card_w1" x="1621" y="1804" width="200" height="74" pivotX="0" pivotY="0"/>
	<SubTexture name="card_wm1" x="2781" y="1806" width="200" height="74" pivotX="0" pivotY="0"/>
	<SubTexture name="chest_icon" x="1287" y="1479" width="70" height="51" pivotX="0" pivotY="0"/>
	<SubTexture name="chip_blue" x="4043" y="57" width="52" height="52" pivotX="0" pivotY="0"/>
	<SubTexture name="chip_chest" x="4033" y="507" width="53" height="52" pivotX="0" pivotY="0"/>
	<SubTexture name="chip_fire" x="4033" y="450" width="53" height="56" pivotX="0" pivotY="0"/>
	<SubTexture name="chip_green" x="4043" y="110" width="52" height="52" pivotX="0" pivotY="0"/>
	<SubTexture name="chip_red" x="4043" y="163" width="51" height="52" pivotX="0" pivotY="0"/>
	<SubTexture name="chip_select" x="4033" y="608" width="48" height="48" pivotX="0" pivotY="0"/>
	<SubTexture name="chip_sword" x="4043" y="1" width="52" height="55" pivotX="0" pivotY="0"/>
	<SubTexture name="chip_white" x="4043" y="216" width="51" height="51" pivotX="0" pivotY="0"/>
	<SubTexture name="common_back" x="3979" y="792" width="101" height="101" pivotX="0" pivotY="0"/>
	<SubTexture name="common_button_back1" x="2781" y="1772" width="137" height="30" pivotX="0" pivotY="0"/>
	<SubTexture name="common_button_back2" x="1822" y="1804" width="137" height="30" pivotX="0" pivotY="0"/>
	<SubTexture name="common_button_over" x="384" y="1538" width="32" height="25" pivotX="0" pivotY="0"/>
	<SubTexture name="common_button_up" x="1420" y="1736" width="32" height="25" pivotX="0" pivotY="0"/>
	<SubTexture name="common_disabled_tint" x="887" y="1821" width="43" height="42" pivotX="0" pivotY="0"/>
	<SubTexture name="common_hitrect" x="4043" y="268" width="50" height="50" pivotX="0" pivotY="0"/>
	<SubTexture name="common_icon_close" x="4073" y="1115" width="21" height="21" pivotX="0" pivotY="0"/>
	<SubTexture name="common_killed" x="1287" y="1549" width="169" height="169" pivotX="0" pivotY="0"/>
	<SubTexture name="common_next" x="1018" y="1539" width="27" height="67" pivotX="0" pivotY="0"/>
	<SubTexture name="common_scroll_arrow" x="4073" y="1137" width="19" height="18" pivotX="0" pivotY="0"/>
	<SubTexture name="common_tick" x="4074" y="757" width="21" height="27" pivotX="0" pivotY="0"/>
	<SubTexture name="common_trap_back" x="1018" y="1607" width="29" height="39" pivotX="0" pivotY="0"/>
	<SubTexture name="common_trap_icon" x="4073" y="1175" width="19" height="17" pivotX="0" pivotY="0"/>
	<SubTexture name="drop_body" x="4033" y="393" width="55" height="56" pivotX="0" pivotY="0"/>
	<SubTexture name="drop_boots" x="4033" y="707" width="41" height="49" pivotX="0" pivotY="0"/>
	<SubTexture name="drop_gloves" x="1726" y="1564" width="65" height="37" pivotX="0" pivotY="0"/>
	<SubTexture name="drop_gold" x="4033" y="757" width="40" height="34" pivotX="0" pivotY="0"/>
	<SubTexture name="drop_magic" x="4033" y="560" width="57" height="47" pivotX="0" pivotY="0"/>
	<SubTexture name="drop_pants" x="4033" y="657" width="46" height="49" pivotX="0" pivotY="0"/>
	<SubTexture name="drop_ring" x="4050" y="894" width="33" height="26" pivotX="0" pivotY="0"/>
	<SubTexture name="drop_shield" x="3222" y="1862" width="71" height="44" pivotX="0" pivotY="0"/>
	<SubTexture name="drop_staff" x="3143" y="1862" width="78" height="53" pivotX="0" pivotY="0"/>
	<SubTexture name="drop_sword" x="3061" y="1862" width="81" height="52" pivotX="0" pivotY="0"/>
	<SubTexture name="exp_progress_line" x="3294" y="1862" width="152" height="16" pivotX="0" pivotY="0"/>
	<SubTexture name="h1" x="1658" y="1654" width="118" height="83" pivotX="0" pivotY="0"/>
	<SubTexture name="h2" x="1607" y="1564" width="118" height="89" pivotX="0" pivotY="0"/>
	<SubTexture name="h3" x="1457" y="1564" width="149" height="123" pivotX="0" pivotY="0"/>
	<SubTexture name="hero.png" x="1" y="1538" width="186" height="253" pivotX="0" pivotY="0"/>
	<SubTexture name="hud_bg_1" x="1977" y="1731" width="1000" height="40" pivotX="0" pivotY="0"/>
	<SubTexture name="impact_21.png" x="1797" y="1239" width="256" height="256" pivotX="0" pivotY="0"/>
	<SubTexture name="impact_49.png" x="3722" y="792" width="256" height="128" pivotX="0" pivotY="0"/>
	<SubTexture name="inventory_player_set_bg" x="1591" y="1239" width="205" height="324" pivotX="0" pivotY="0"/>
	<SubTexture name="item_body" x="2982" y="1806" width="205" height="55" pivotX="0" pivotY="0"/>
	<SubTexture name="item_boots" x="3188" y="1806" width="205" height="55" pivotX="0" pivotY="0"/>
	<SubTexture name="item_gloves" x="3394" y="1806" width="205" height="55" pivotX="0" pivotY="0"/>
	<SubTexture name="item_helmet" x="3600" y="1806" width="205" height="55" pivotX="0" pivotY="0"/>
	<SubTexture name="item_pants" x="3806" y="1806" width="205" height="55" pivotX="0" pivotY="0"/>
	<SubTexture name="item_ring" x="950" y="1814" width="205" height="55" pivotX="0" pivotY="0"/>
	<SubTexture name="item_select" x="1" y="1857" width="203" height="53" pivotX="0" pivotY="0"/>
	<SubTexture name="item_staff" x="1156" y="1814" width="205" height="55" pivotX="0" pivotY="0"/>
	<SubTexture name="item_sword" x="1621" y="1804" width="200" height="74" pivotX="0" pivotY="0"/>
	<SubTexture name="itemicon_magicshield" x="1621" y="1763" width="32" height="34" pivotX="0" pivotY="0"/>
	<SubTexture name="itemicon_shield" x="3652" y="1862" width="28" height="34" pivotX="0" pivotY="0"/>
	<SubTexture name="itemicon_spell" x="1018" y="1687" width="33" height="34" pivotX="0" pivotY="0"/>
	<SubTexture name="itemmagic_back" x="3979" y="894" width="70" height="17" pivotX="0" pivotY="0"/>
	<SubTexture name="itemmagic_blue" x="4075" y="744" width="16" height="5" pivotX="0" pivotY="0"/>
	<SubTexture name="itemmagic_green" x="4075" y="750" width="17" height="4" pivotX="0" pivotY="0"/>
	<SubTexture name="itemmagic_orange" x="4074" y="785" width="17" height="4" pivotX="0" pivotY="0"/>
	<SubTexture name="itemmagic_red" x="3979" y="912" width="17" height="4" pivotX="0" pivotY="0"/>
	<SubTexture name="itemmagic_white" x="3997" y="912" width="17" height="4" pivotX="0" pivotY="0"/>
	<SubTexture name="letter_C" x="4073" y="1034" width="21" height="26" pivotX="0" pivotY="0"/>
	<SubTexture name="letter_D" x="4073" y="1061" width="21" height="26" pivotX="0" pivotY="0"/>
	<SubTexture name="letter_L" x="4077" y="921" width="18" height="26" pivotX="0" pivotY="0"/>
	<SubTexture name="letter_M" x="152" y="1830" width="24" height="25" pivotX="0" pivotY="0"/>
	<SubTexture name="letter_V" x="4073" y="1088" width="21" height="26" pivotX="0" pivotY="0"/>
	<SubTexture name="letter_X" x="4073" y="1007" width="22" height="26" pivotX="0" pivotY="0"/>
	<SubTexture name="level_1" x="4077" y="948" width="17" height="26" pivotX="0" pivotY="0"/>
	<SubTexture name="level_2" x="2047" y="1496" width="23" height="26" pivotX="0" pivotY="0"/>
	<SubTexture name="level_3" x="2919" y="1772" width="27" height="26" pivotX="0" pivotY="0"/>
	<SubTexture name="level_4" x="2947" y="1772" width="26" height="26" pivotX="0" pivotY="0"/>
	<SubTexture name="magic_dark" x="1362" y="1838" width="205" height="55" pivotX="0" pivotY="0"/>
	<SubTexture name="magic_earth" x="1822" y="1847" width="205" height="55" pivotX="0" pivotY="0"/>
	<SubTexture name="magic_fire" x="2028" y="1847" width="205" height="55" pivotX="0" pivotY="0"/>
	<SubTexture name="magic_green" x="2234" y="1847" width="205" height="55" pivotX="0" pivotY="0"/>
	<SubTexture name="magic_water" x="2440" y="1847" width="205" height="55" pivotX="0" pivotY="0"/>
	<SubTexture name="mana_blue" x="741" y="1572" width="54" height="37" pivotX="0" pivotY="0"/>
	<SubTexture name="mana_fire" x="1726" y="1602" width="54" height="37" pivotX="0" pivotY="0"/>
	<SubTexture name="mana_green" x="123" y="1792" width="54" height="37" pivotX="0" pivotY="0"/>
	<SubTexture name="mana_red" x="1568" y="1838" width="44" height="41" pivotX="0" pivotY="0"/>
	<SubTexture name="mana_white" x="3607" y="1862" width="44" height="35" pivotX="0" pivotY="0"/>
	<SubTexture name="map_background" x="1" y="1" width="2069" height="1237" pivotX="0" pivotY="0"/>
	<SubTexture name="map_cloud" x="1" y="1239" width="421" height="298" pivotX="0" pivotY="0"/>
	<SubTexture name="map_hud_bitmap" x="384" y="1572" width="356" height="59" pivotX="0" pivotY="0"/>
	<SubTexture name="map_hud_house0" x="2726" y="1847" width="39" height="41" pivotX="0" pivotY="0"/>
	<SubTexture name="map_hud_house1" x="3568" y="1862" width="38" height="41" pivotX="0" pivotY="0"/>
	<SubTexture name="map_hud_star1" x="4073" y="1156" width="19" height="18" pivotX="0" pivotY="0"/>
	<SubTexture name="map_hud_star2" x="4080" y="657" width="15" height="14" pivotX="0" pivotY="0"/>
	<SubTexture name="map_hud_star3" x="4080" y="657" width="15" height="14" pivotX="0" pivotY="0"/>
	<SubTexture name="map_hud_stars_back" x="4043" y="370" width="45" height="18" pivotX="0" pivotY="0"/>
	<SubTexture name="map_icon_back" x="1018" y="1647" width="29" height="39" pivotX="0" pivotY="0"/>
	<SubTexture name="map_timer_back" x="3722" y="921" width="354" height="85" pivotX="0" pivotY="0"/>
	<SubTexture name="monster_1.png" x="1977" y="1496" width="69" height="221" pivotX="0" pivotY="0"/>
	<SubTexture name="monster_10.png" x="3722" y="1" width="320" height="391" pivotX="0" pivotY="0"/>
	<SubTexture name="monster_2.png" x="3722" y="393" width="310" height="398" pivotX="0" pivotY="0"/>
	<SubTexture name="monster_3.png" x="798" y="1239" width="255" height="299" pivotX="0" pivotY="0"/>
	<SubTexture name="monster_4.png" x="1364" y="1239" width="226" height="309" pivotX="0" pivotY="0"/>
	<SubTexture name="monster_5.png" x="950" y="1539" width="67" height="254" pivotX="0" pivotY="0"/>
	<SubTexture name="monster_6.png" x="423" y="1239" width="374" height="332" pivotX="0" pivotY="0"/>
	<SubTexture name="monster_7.png" x="1797" y="1496" width="179" height="307" pivotX="0" pivotY="0"/>
	<SubTexture name="monster_8.png" x="1054" y="1239" width="309" height="239" pivotX="0" pivotY="0"/>
	<SubTexture name="monster_9.png" x="798" y="1539" width="151" height="281" pivotX="0" pivotY="0"/>
	<SubTexture name="monster_icon_1" x="2646" y="1847" width="79" height="76" pivotX="0" pivotY="0"/>
	<SubTexture name="monster_icon_10" x="696" y="1857" width="80" height="60" pivotX="0" pivotY="0"/>
	<SubTexture name="monster_icon_2" x="4012" y="1797" width="81" height="79" pivotX="0" pivotY="0"/>
	<SubTexture name="monster_icon_3" x="286" y="1857" width="89" height="64" pivotX="0" pivotY="0"/>
	<SubTexture name="monster_icon_4" x="455" y="1857" width="80" height="69" pivotX="0" pivotY="0"/>
	<SubTexture name="monster_icon_5" x="536" y="1857" width="79" height="67" pivotX="0" pivotY="0"/>
	<SubTexture name="monster_icon_6" x="2982" y="1862" width="78" height="55" pivotX="0" pivotY="0"/>
	<SubTexture name="monster_icon_7" x="376" y="1857" width="78" height="72" pivotX="0" pivotY="0"/>
	<SubTexture name="monster_icon_8" x="1658" y="1738" width="117" height="65" pivotX="0" pivotY="0"/>
	<SubTexture name="monster_icon_9" x="616" y="1857" width="79" height="65" pivotX="0" pivotY="0"/>
	<SubTexture name="player_hero" x="188" y="1538" width="195" height="240" pivotX="0" pivotY="0"/>
	<SubTexture name="step_icon" x="1607" y="1654" width="40" height="31" pivotX="0" pivotY="0"/>
	<SubTexture name="tint" x="4043" y="319" width="50" height="50" pivotX="0" pivotY="0"/>
</TextureAtlas>
