[
    {
        "level": 1,
        "id": "pikachu",
        "hp": 20,
        "damage": 3,
        "damagetype": "weapon",
        "defence": 2,
        "magic": 3,
        "difficulty": 100,
        "drop": 1,
        "items": 13,
        "stars": "5,10,20",
        "picture": "monster_1.png",
        "expearned": 5,
        "speed": 100,
        "reward": 100
    },
    {
        "level": 1,
        "id": "blue_bull",
        "hp": 29,
        "damage": 4,
        "damagetype": "weapon",
        "defence": 3,
        "magic": 3,
        "difficulty": 100,
        "drop": 1,
        "items": 13,
        "stars": "5,10,20",
        "picture": "monster_2.png",
        "expearned": 10,
        "speed": 100,
        "reward": 500
    },
    {
        "level": 1,
        "id": "meowut",
        "hp": 38,
        "damage": 8,
        "damagetype": "weapon",
        "defence": 5,
        "magic": 3,
        "difficulty": 100,
        "drop": 1,
        "items": 13,
        "stars": "5,10,20",
        "picture": "monster_4.png",
        "expearned": 17,
        "speed": 100,
        "reward": 500
    },
    {
        "level": 1,
        "id": "slowpoke",
        "hp": 52,
        "damage": 12,
        "damagetype": "weapon",
        "defence": 8,
        "magic": 3,
        "difficulty": 100,
        "drop": 1,
        "items": 13,
        "stars": "5,10,20",
        "picture": "monster_3.png",
        "expearned": 31,
        "speed": 100,
        "reward": 500
    },
    {
        "level": 1,
        "id": "squirtle",
        "hp": 66,
        "damage": 17,
        "damagetype": "weapon",
        "defence": 12,
        "magic": 3,
        "difficulty": 100,
        "drop": 1,
        "items": 13,
        "stars": "5,10,20",
        "picture": "monster_7.png",
        "expearned": 52,
        "speed": 100,
        "reward": 500
    },
    {
        "level": 1,
        "id": "charmander",
        "hp": 79,
        "damage": 23,
        "damagetype": "weapon",
        "defence": 16,
        "magic": 3,
        "difficulty": 100,
        "drop": 1,
        "items": 13,
        "stars": "5,10,20",
        "picture": "monster_5.png",
        "expearned": 84,
        "speed": 100,
        "reward": 500
    },
    {
        "level": 1,
        "id": "bulbasaur",
        "hp": 89,
        "damage": 29,
        "damagetype": "weapon",
        "defence": 20,
        "magic": 3,
        "difficulty": 100,
        "drop": 1,
        "items": 13,
        "stars": "5,10,20",
        "picture": "monster_6.png",
        "expearned": 126,
        "speed": 100,
        "reward": 500
    },
    {
        "level": 1,
        "id": "pidgey",
        "hp": 94,
        "damage": 37,
        "damagetype": "weapon",
        "defence": 26,
        "magic": 3,
        "difficulty": 100,
        "drop": 1,
        "items": 13,
        "stars": "5,10,20",
        "picture": "monster_8.png",
        "expearned": 176,
        "speed": 100,
        "reward": 500
    },
    {
        "level": 1,
        "id": "ratata",
        "hp": 99,
        "damage": 40,
        "damagetype": "weapon",
        "defence": 28,
        "magic": 3,
        "difficulty": 100,
        "drop": 1,
        "items": 13,
        "stars": "5,10,20",
        "picture": "monster_9.png",
        "expearned": 246,
        "speed": 100,
        "reward": 500
    },
    {
        "level": 1,
        "id": "zubat",
        "hp": 148,
        "damage": 63,
        "damagetype": "weapon",
        "defence": 44,
        "magic": 3,
        "difficulty": 100,
        "drop": 1,
        "items": 13,
        "stars": "5,10,20",
        "picture": "monster_10.png",
        "expearned": 492,
        "speed": 100,
        "reward": 500
    }
]